<annotation><filename>01565765335235.jpg</filename><folder>train</folder><object><bndbox><xmax>306</xmax><xmin>267</xmin><ymax>253</ymax><ymin>189</ymin></bndbox><difficult>0</difficult><name>mh 3</name><pose>Unspecified</pose><truncated>0</truncated></object><object><bndbox><xmax>450</xmax><xmin>416</xmin><ymax>426</ymax><ymin>360</ymin></bndbox><difficult>0</difficult><name>mh 3</name><pose>Unspecified</pose><truncated>0</truncated></object><path>c:\models\research\object_detection\images\train\01565765335235.jpg</path><segmented>0</segmented><size><depth>3</depth><height>480</height><width>640</width></size><source><database>Unknown</database></source></annotation>