<annotation><filename>11565766549990.jpg</filename><folder>train</folder><object><bndbox><xmax>164</xmax><xmin>93</xmin><ymax>412</ymax><ymin>372</ymin></bndbox><difficult>0</difficult><name>ht 3</name><pose>Unspecified</pose><truncated>0</truncated></object><object><bndbox><xmax>377</xmax><xmin>307</xmin><ymax>255</ymax><ymin>220</ymin></bndbox><difficult>0</difficult><name>ht 3</name><pose>Unspecified</pose><truncated>0</truncated></object><path>c:\models\research\object_detection\images\train\11565766549990.jpg</path><segmented>0</segmented><size><depth>3</depth><height>480</height><width>640</width></size><source><database>Unknown</database></source></annotation>