<annotation><filename>11565766565026.jpg</filename><folder>train</folder><object><bndbox><xmax>313</xmax><xmin>248</xmin><ymax>332</ymax><ymin>298</ymin></bndbox><difficult>0</difficult><name>ht 3</name><pose>Unspecified</pose><truncated>0</truncated></object><object><bndbox><xmax>485</xmax><xmin>393</xmin><ymax>165</ymax><ymin>117</ymin></bndbox><difficult>0</difficult><name>ht 3</name><pose>Unspecified</pose><truncated>0</truncated></object><path>c:\models\research\object_detection\images\train\11565766565026.jpg</path><segmented>0</segmented><size><depth>3</depth><height>480</height><width>640</width></size><source><database>Unknown</database></source></annotation>