<annotation><filename>1566201857231.jpg</filename><folder>train</folder><object><bndbox><xmax>526</xmax><xmin>336</xmin><ymax>136</ymax><ymin>51</ymin></bndbox><difficult>0</difficult><name>hx 4</name><pose>Unspecified</pose><truncated>0</truncated></object><object><bndbox><xmax>97</xmax><xmin>3</xmin><ymax>464</ymax><ymin>401</ymin></bndbox><difficult>0</difficult><name>hx 4</name><pose>Unspecified</pose><truncated>0</truncated></object><path>c:\models\research\object_detection\images\train\1566201857231.jpg</path><segmented>0</segmented><size><depth>3</depth><height>480</height><width>640</width></size><source><database>Unknown</database></source></annotation>