<annotation><filename>41566195337572.jpg</filename><folder>train</folder><object><bndbox><xmax>209</xmax><xmin>117</xmin><ymax>224</ymax><ymin>177</ymin></bndbox><difficult>0</difficult><name>mh 4</name><pose>Unspecified</pose><truncated>0</truncated></object><object><bndbox><xmax>573</xmax><xmin>424</xmin><ymax>47</ymax><ymin>0</ymin></bndbox><difficult>0</difficult><name>mh 4</name><pose>Unspecified</pose><truncated>0</truncated></object><path>c:\models\research\object_detection\images\train\41566195337572.jpg</path><segmented>0</segmented><size><depth>3</depth><height>480</height><width>640</width></size><source><database>Unknown</database></source></annotation>