<annotation><filename>61565948856385.jpg</filename><folder>train</folder><object><bndbox><xmax>170</xmax><xmin>86</xmin><ymax>339</ymax><ymin>289</ymin></bndbox><difficult>0</difficult><name>fk 9</name><pose>Unspecified</pose><truncated>0</truncated></object><object><bndbox><xmax>515</xmax><xmin>364</xmin><ymax>139</ymax><ymin>66</ymin></bndbox><difficult>0</difficult><name>fk 9</name><pose>Unspecified</pose><truncated>0</truncated></object><path>c:\models\research\object_detection\images\train\61565948856385.jpg</path><segmented>0</segmented><size><depth>3</depth><height>480</height><width>640</width></size><source><database>Unknown</database></source></annotation>