<annotation><filename>81565765358291.jpg</filename><folder>train</folder><object><bndbox><xmax>240</xmax><xmin>172</xmin><ymax>254</ymax><ymin>218</ymin></bndbox><difficult>0</difficult><name>mh 4</name><pose>Unspecified</pose><truncated>0</truncated></object><object><bndbox><xmax>490</xmax><xmin>411</xmin><ymax>162</ymax><ymin>124</ymin></bndbox><difficult>0</difficult><name>mh 4</name><pose>Unspecified</pose><truncated>0</truncated></object><path>c:\models\research\object_detection\images\train\81565765358291.jpg</path><segmented>0</segmented><size><depth>3</depth><height>480</height><width>640</width></size><source><database>Unknown</database></source></annotation>