<annotation><filename>81565949911706.jpg</filename><folder>train</folder><object><bndbox><xmax>594</xmax><xmin>492</xmin><ymax>139</ymax><ymin>99</ymin></bndbox><difficult>0</difficult><name>fk j</name><pose>Unspecified</pose><truncated>0</truncated></object><object><bndbox><xmax>268</xmax><xmin>150</xmin><ymax>370</ymax><ymin>324</ymin></bndbox><difficult>0</difficult><name>fk j</name><pose>Unspecified</pose><truncated>0</truncated></object><path>c:\models\research\object_detection\images\train\81565949911706.jpg</path><segmented>0</segmented><size><depth>3</depth><height>480</height><width>640</width></size><source><database>Unknown</database></source></annotation>